aa_forum/__init__.py
aa_forum/admin.py
aa_forum/app_settings.py
aa_forum/apps.py
aa_forum/auth_hooks.py
aa_forum/constants.py
aa_forum/forms.py
aa_forum/managers.py
aa_forum/models.py
aa_forum/providers.py
aa_forum/signals.py
aa_forum/helper/discord_messages.py
aa_forum/helper/eve_images.py
aa_forum/helper/forms.py
aa_forum/helper/pagination.py
aa_forum/helper/text.py
aa_forum/helper/urls.py
aa_forum/helper/user.py
aa_forum/locale/django.pot
aa_forum/locale/cs_CZ/LC_MESSAGES/django.mo
aa_forum/locale/cs_CZ/LC_MESSAGES/django.po
aa_forum/locale/de/LC_MESSAGES/django.mo
aa_forum/locale/de/LC_MESSAGES/django.po
aa_forum/locale/es/LC_MESSAGES/django.mo
aa_forum/locale/es/LC_MESSAGES/django.po
aa_forum/locale/fr_FR/LC_MESSAGES/django.mo
aa_forum/locale/fr_FR/LC_MESSAGES/django.po
aa_forum/locale/it_IT/LC_MESSAGES/django.mo
aa_forum/locale/it_IT/LC_MESSAGES/django.po
aa_forum/locale/ja/LC_MESSAGES/django.mo
aa_forum/locale/ja/LC_MESSAGES/django.po
aa_forum/locale/ko_KR/LC_MESSAGES/django.mo
aa_forum/locale/ko_KR/LC_MESSAGES/django.po
aa_forum/locale/nl_NL/LC_MESSAGES/django.mo
aa_forum/locale/nl_NL/LC_MESSAGES/django.po
aa_forum/locale/pl_PL/LC_MESSAGES/django.mo
aa_forum/locale/pl_PL/LC_MESSAGES/django.po
aa_forum/locale/ru/LC_MESSAGES/django.mo
aa_forum/locale/ru/LC_MESSAGES/django.po
aa_forum/locale/sk/LC_MESSAGES/django.mo
aa_forum/locale/sk/LC_MESSAGES/django.po
aa_forum/locale/uk/LC_MESSAGES/django.mo
aa_forum/locale/uk/LC_MESSAGES/django.po
aa_forum/locale/zh_Hans/LC_MESSAGES/django.mo
aa_forum/locale/zh_Hans/LC_MESSAGES/django.po
aa_forum/migrations/0001_initial.py
aa_forum/migrations/0002_default_settings.py
aa_forum/migrations/0003_board_discord_webhook.py
aa_forum/migrations/0004_board_use_webhook_for_replies.py
aa_forum/migrations/0005_announcement_boards.py
aa_forum/migrations/0006_reset_default_settings.py
aa_forum/migrations/0007_change_settings_to_singleton.py
aa_forum/migrations/0008_populate_default_settings.py
aa_forum-2.14.2.dist-info/METADATA
aa_forum-2.14.2.dist-info/WHEEL
aa_forum-2.14.2.dist-info/licenses/LICENSE
aa_forum-2.14.2.dist-info/RECORD
